{"skeleton":{"hash":"Oj1iEOWRwaFxOZbX5LMqB3RERyU","spine":"2.1.27","width":240.64,"height":61.44,"images":""},"bones":[{"name":"root"},{"name":"placeholder","parent":"root","x":640,"y":-300,"scaleX":0.001,"scaleY":0.001},{"name":"shadowglow","parent":"root","x":640,"y":-296,"scaleX":0.94,"scaleY":-0.24}],"slots":[{"name":"shadowglow","bone":"shadowglow","color":"ffffff00","attachment":"assets/shadowglow","blend":"multiply"},{"name":"placeholder","bone":"placeholder","color":"ffffff00","attachment":"assets/placeholder"}],"skins":{"default":{"placeholder":{"assets/placeholder":{"width":467,"height":187}},"shadowglow":{"assets/shadowglow":{"width":256,"height":256}}}},"animations":{"animation":{"slots":{"placeholder":{"color":[{"time":0.0666,"color":"ffffff00"},{"time":0.2666,"color":"ffffffff","curve":"stepped"},{"time":1.7333,"color":"ffffffff"},{"time":1.8666,"color":"ffffff00"}]},"shadowglow":{"color":[{"time":0.0666,"color":"ffffff00"},{"time":0.2666,"color":"ffffffcc","curve":"stepped"},{"time":1.7333,"color":"ffffffcc"},{"time":1.8666,"color":"ffffff00"}]}},"bones":{"shadowglow":{"scale":[{"time":0,"x":1,"y":1},{"time":0.2666,"x":2.063,"y":-3.166},{"time":1.7333,"x":2.595,"y":-5.25},{"time":1.9333,"x":4.191,"y":-11.5}]},"placeholder":{"scale":[{"time":0,"x":0,"y":0},{"time":0.2666,"x":1000,"y":1000},{"time":1.7333,"x":1500,"y":1500},{"time":1.9333,"x":3000,"y":3000}]}}}}}